setup.py
Abdullah_probability/Binomialdistribution.py
Abdullah_probability/Gaussiandistribution.py
Abdullah_probability/Generaldistribution.py
Abdullah_probability/__init__.py
Abdullah_probability.egg-info/PKG-INFO
Abdullah_probability.egg-info/SOURCES.txt
Abdullah_probability.egg-info/dependency_links.txt
Abdullah_probability.egg-info/not-zip-safe
Abdullah_probability.egg-info/top_level.txt